nutaan/__init__.py
nutaan/__main__.py
nutaan/cli.py
nutaan/core/__init__.py
nutaan/core/agent_manager.py
nutaan/core/approval_agent_wrapper.py
nutaan/core/config_manager.py
nutaan/core/llm_manager.py
nutaan/core/prompt_system.py
nutaan/core/session_history.py
nutaan/core/tool_approval_manager.py
nutaan/tools/__init__.py
nutaan/tools/bash_run_tool.py
nutaan/tools/brave_search_tool.py
nutaan/tools/file_edit_tool.py
nutaan/tools/file_edit_utils.py
nutaan/tools/file_read_tool.py
nutaan/tools/file_timestamp_manager.py
nutaan/tools/file_write_tool.py
nutaan/tools/plan_tool.py
nutaan/tools/think_tool.py
nutaan_cli-1.0.1.dist-info/licenses/LICENSE
nutaan_cli-1.0.1.dist-info/METADATA
nutaan_cli-1.0.1.dist-info/WHEEL
nutaan_cli-1.0.1.dist-info/entry_points.txt
nutaan_cli-1.0.1.dist-info/top_level.txt
nutaan_cli-1.0.1.dist-info/RECORD
