Metadata-Version: 2.4
Name: nutaan-cli
Version: 1.0.1
Summary: A powerful ReAct Python Assistant with AI capabilities
Author-email: Tecosys <info@tecosys.in>
License: MIT
Project-URL: Homepage, https://github.com/Tecosys/nutaan-cli
Project-URL: Documentation, https://github.com/Tecosys/nutaan-cli/blob/main/README.md
Project-URL: Repository, https://github.com/Tecosys/nutaan-cli
Project-URL: Bug Reports, https://github.com/Tecosys/nutaan-cli/issues
Keywords: ai,assistant,react,python,langchain,openai,claude
Classifier: Development Status :: 4 - Beta
Classifier: Intended Audience :: Developers
Classifier: Topic :: Software Development :: Libraries :: Python Modules
Classifier: Topic :: Scientific/Engineering :: Artificial Intelligence
Classifier: Programming Language :: Python :: 3
Classifier: Programming Language :: Python :: 3.8
Classifier: Programming Language :: Python :: 3.9
Classifier: Programming Language :: Python :: 3.10
Classifier: Programming Language :: Python :: 3.11
Classifier: Programming Language :: Python :: 3.12
Requires-Python: >=3.8
License-File: LICENSE
Requires-Dist: langchain>=0.3.0
Requires-Dist: langchain-openai>=0.2.0
Requires-Dist: langchain-core>=0.3.0
Requires-Dist: langgraph>=0.5.0
Requires-Dist: requests>=2.25.0
Requires-Dist: pydantic>=2.0.0
Requires-Dist: rich>=13.0.0
Provides-Extra: dev
Requires-Dist: pytest>=6.0; extra == "dev"
Requires-Dist: black; extra == "dev"
Requires-Dist: flake8; extra == "dev"
Requires-Dist: mypy; extra == "dev"
Dynamic: license-file
